JaStopwordFilter.py
__init__.py
jp_stopword_filter-0.2.0.dist-info/METADATA
jp_stopword_filter-0.2.0.dist-info/WHEEL
jp_stopword_filter-0.2.0.dist-info/entry_points.txt
jp_stopword_filter-0.2.0.dist-info/licenses/LICENSE
jp_stopword_filter-0.2.0.dist-info/RECORD
