Metadata-Version: 2.1
Name: jp-stopword-filter
Version: 0.2.0
Summary: A lightweight Python library designed to filter stopwords for Japanese text.
Author-Email: BrambleXu <liangxu006@gmail.com>
License: Apache-2.0
Requires-Python: >=3.9
Requires-Dist: numpy>=1.26.4
